learnify/__init__.py
learnify/main.py
learnify/prompts.py
learnify-2025.12.21123742.dist-info/METADATA
learnify-2025.12.21123742.dist-info/WHEEL
learnify-2025.12.21123742.dist-info/top_level.txt
learnify-2025.12.21123742.dist-info/RECORD
