Metadata-Version: 2.4
Name: learnify
Version: 2025.12.21123742
Summary: A new package that helps software developers improve their learning strategies by analyzing their self-reported learning habits, goals, and challenges. It takes text input describing their current lea
Author-email: learnify <hi@eugene.plus>
License: MIT
Project-URL: Homepage, https://github.com/chigwell/learnify
Requires-Python: >=3.9
Requires-Dist: langchain-llm7>=0.0.0
Requires-Dist: llmatch-messages>=0.0.0
Requires-Dist: langchain-core>=0.3.0
